UBD/UBD.py.py
UBD/__init__.py
UmBokDong-1.dist-info/METADATA
UmBokDong-1.dist-info/WHEEL
UmBokDong-1.dist-info/top_level.txt
UmBokDong-1.dist-info/RECORD
