Metadata-Version: 2.1
Name: UmBokDong
Version: 1
Summary: 엄복동 구하기
Home-page: 
Author: Jason Choi
Author-email: orangecolver@gmail.com
Requires-Python: >=3
